aiodog/__init__.py
aiodog/client.py
aiodog.py-0.2.0.dist-info/LICENSE
aiodog.py-0.2.0.dist-info/WHEEL
aiodog.py-0.2.0.dist-info/METADATA
aiodog.py-0.2.0.dist-info/RECORD
